odoo/addons/product_supplierinfo_archive/README.rst
odoo/addons/product_supplierinfo_archive/__init__.py
odoo/addons/product_supplierinfo_archive/__manifest__.py
odoo/addons/product_supplierinfo_archive/i18n/it.po
odoo/addons/product_supplierinfo_archive/i18n/product_supplierinfo_archive.pot
odoo/addons/product_supplierinfo_archive/models/__init__.py
odoo/addons/product_supplierinfo_archive/models/product_supplierinfo.py
odoo/addons/product_supplierinfo_archive/readme/CONTRIBUTORS.rst
odoo/addons/product_supplierinfo_archive/readme/DESCRIPTION.rst
odoo/addons/product_supplierinfo_archive/readme/USAGE.rst
odoo/addons/product_supplierinfo_archive/static/description/icon.png
odoo/addons/product_supplierinfo_archive/static/description/index.html
odoo/addons/product_supplierinfo_archive/views/product_views.xml
odoo13_addon_product_supplierinfo_archive-13.0.1.0.1.dev7.dist-info/METADATA
odoo13_addon_product_supplierinfo_archive-13.0.1.0.1.dev7.dist-info/WHEEL
odoo13_addon_product_supplierinfo_archive-13.0.1.0.1.dev7.dist-info/top_level.txt
odoo13_addon_product_supplierinfo_archive-13.0.1.0.1.dev7.dist-info/RECORD
